{
    "2018/01/01" : {
        "source" : "user1-s",
        "target" : "user1-t"
    },
    "2018/02/01" : {
        "source" : "user2-s",
        "target" : "user2-t"
    },
    "2018/03/01" : {
        "source" : "user3-s",
        "target" : "user3-t"
    },
    "2018/04/01" : {
        "source" : "user4-s",
        "target" : "user4-t"
    },
    "2018/05/01" : {
        "source" : "user5-s",
        "target" : "user5-t"
    },
    "2018/06/01" : {
        "source" : "user6-s",
        "target" : "user6-t"
    },
    "2018/07/01" : {
        "source" : "user7-s",
        "target" : "user7-t"
    },
    "2018/08/01" : {
        "source" : "user8-s",
        "target" : "user8-t"
    },
    "2018/09/01" : {
        "source" : "user9-s",
        "target" : "user9-t"
    },
    "2018/10/01" : {
        "source" : "user10-s",
        "target" : "user10-t"
    },
    "2018/11/01" : {
        "source" : "user11-s",
        "target" : "user11-t"
    },
    "2018/12/01" : {
        "source" : "user12-s",
        "target" : "user12-t"
    }
}

